{
  "project_info": {
    "project_number": "1051050743421",
    "project_id": "finalprojectmobile1",
    "storage_bucket": "finalprojectmobile1.appspot.com"
  },
  "client": [
    {
      "client_info": {
        "mobilesdk_app_id": "1:1051050743421:android:159067ce46004da8e5c314",
        "android_client_info": {
          "package_name": "com.example.flutter_finalproject"
        }
      },
      "oauth_client": [
        {
          "client_id": "1051050743421-vjoiechbv9649mcpk7gd7o34186ukhov.apps.googleusercontent.com",
          "client_type": 3
        }
      ],
      "api_key": [
        {
          "current_key": "AIzaSyAjAGwkkIcLuAGWRdxbQgy_XdfQVXgPUlo"
        }
      ],
      "services": {
        "appinvite_service": {
          "other_platform_oauth_client": [
            {
              "client_id": "1051050743421-vjoiechbv9649mcpk7gd7o34186ukhov.apps.googleusercontent.com",
              "client_type": 3
            }
          ]
        }
      }
    }
  ],
  "configuration_version": "1"
}